{
  "db_name": "PostgreSQL",
  "query": "UPDATE audio_files\n            SET end_ts = start_ts,\n                reaped = TRUE,\n                recording_heartbeat_at = NULL,\n                finalize_reason_id = $1\n          WHERE end_ts IS NULL\n            AND NOT EXISTS (\n                SELECT 1\n                  FROM bot_instances bi\n                 WHERE bi.instance_id = audio_files.recording_owner_instance_id\n                   AND audio_files.recording_heartbeat_at > now() - ($2::double precision * interval '1 second')\n                   AND bi.heartbeat_at > now() - ($2::double precision * interval '1 second')\n                   AND bi.state <> 'stopped'\n            )",
  "describe": {
    "columns": [],
    "parameters": {
      "Left": [
        "Int4",
        "Float8"
      ]
    },
    "nullable": []
  },
  "hash": "2f35f96297078fe319e51b054da4222ec90e74d333738716329868d593697017"
}
